pylasr_sdk/__init__.py
pylasr_sdk/inputs.py
pylasr_sdk/outputs.py
pylasr_sdk-0.1.5.dist-info/LICENSE
pylasr_sdk-0.1.5.dist-info/METADATA
pylasr_sdk-0.1.5.dist-info/WHEEL
pylasr_sdk-0.1.5.dist-info/top_level.txt
pylasr_sdk-0.1.5.dist-info/RECORD
